LICENSE
README.md
setup.cfg
setup.py
cgxsh.egg-info/PKG-INFO
cgxsh.egg-info/SOURCES.txt
cgxsh.egg-info/dependency_links.txt
cgxsh.egg-info/entry_points.txt
cgxsh.egg-info/requires.txt
cgxsh.egg-info/top_level.txt
cgxsh_lib/__init__.py
cgxsh_lib/defaults.py
cgxsh_lib/file_crypto.py
cgxsh_lib/getch.py