Metadata-Version: 2.1
Name: cgxsh
Version: 1.0.2b1
Summary: Command-line access to the controller-based CloudGenix ION Troubleshooting Toolkit.
Home-page: https://github.com/ebob9/cgxsh
Author: Aaron Edwards
Author-email: cgxsh@ebob9.com
License: MIT
Classifier: Development Status :: 4 - Beta
Classifier: Intended Audience :: System Administrators
Classifier: License :: OSI Approved :: MIT License
Classifier: Programming Language :: Python :: 3.10
Classifier: Programming Language :: Python :: 3.11
Classifier: Programming Language :: Python :: 3.12
Classifier: Operating System :: Microsoft :: Windows :: Windows 10
Classifier: Operating System :: Microsoft :: Windows :: Windows 11
Classifier: Operating System :: MacOS :: MacOS X
Classifier: Operating System :: POSIX :: Linux
Classifier: Operating System :: Other OS
Classifier: Topic :: Terminals
Requires-Python: >=3.10.1
License-File: LICENSE
